{
  "id": "image",
  "type": "SharedSlice",
  "name": "Image",
  "description": "Image",
  "variations": [
    {
      "id": "default",
      "name": "Default",
      "docURL": "...",
      "version": "initial",
      "description": "Default",
      "imageUrl": "",
      "primary": {
        "title": {
          "type": "Text",
          "config": {
            "label": "title",
            "placeholder": ""
          }
        },
        "image": {
          "type": "Image",
          "config": {
            "label": "Image",
            "constraint": {
              "width": 200,
              "height": 200
            },
            "thumbnails": []
          }
        }
      },
      "items": {}
    }
  ]
}